{
"type": "FeatureCollection",
"features": [
{
  "type": "Feature",
  "id": "node/2458181794",
  "properties": {
    "description": "Kantonsbibliothek",
    "emergency": "defibrillator",
    "emergency:phone": "144",
    "indoor": "no",
    "opening_hours": "24/7",
    "id": "node/2458181794"
  },
  "geometry": {
    "type": "Point",
    "coordinates": [
      8.3698712,
      46.9566895
    ]
  }
},
{
  "type": "Feature",
  "id": "node/3608449220",
  "properties": {
    "emergency": "defibrillator",
    "emergency:phone": "144",
    "wheelchair": "yes",
    "id": "node/3608449220"
  },
  "geometry": {
    "type": "Point",
    "coordinates": [
      8.3102743,
      46.9817254
    ]
  }
},
{
  "type": "Feature",
  "id": "node/5401265428",
  "properties": {
    "description": "bei der Sammelstelle Gemeindeparkplatz",
    "emergency": "defibrillator",
    "emergency:phone": "144",
    "indoor": "no",
    "opening_hours": "24/7",
    "id": "node/5401265428"
  },
  "geometry": {
    "type": "Point",
    "coordinates": [
      8.3645563,
      46.9612052
    ]
  }
},
{
  "type": "Feature",
  "id": "node/5723650345",
  "properties": {
    "emergency": "defibrillator",
    "emergency:phone": "144",
    "name": "Schulhaus Pestalozzi",
    "opening_hours": "24/7",
    "id": "node/5723650345"
  },
  "geometry": {
    "type": "Point",
    "coordinates": [
      8.3696857,
      46.9576735
    ]
  }
},
{
  "type": "Feature",
  "id": "node/5859259865",
  "properties": {
    "emergency": "defibrillator",
    "emergency:phone": "144",
    "opening_hours": "24/7",
    "id": "node/5859259865"
  },
  "geometry": {
    "type": "Point",
    "coordinates": [
      8.3843037,
      46.9554125
    ]
  }
},
{
  "type": "Feature",
  "id": "node/5859260420",
  "properties": {
    "description": "Postgebäude",
    "emergency": "defibrillator",
    "emergency:phone": "144",
    "indoor": "no",
    "opening_hours": "24/7",
    "id": "node/5859260420"
  },
  "geometry": {
    "type": "Point",
    "coordinates": [
      8.3672221,
      46.9588231
    ]
  }
},
{
  "type": "Feature",
  "id": "node/6151468472",
  "properties": {
    "description": "Bei Gerätedepot",
    "emergency": "defibrillator",
    "emergency:phone": "144",
    "indoor": "no",
    "opening_hours": "24/7",
    "id": "node/6151468472"
  },
  "geometry": {
    "type": "Point",
    "coordinates": [
      8.3710651,
      46.9551559
    ]
  }
},
{
  "type": "Feature",
  "id": "node/6875363551",
  "properties": {
    "emergency": "defibrillator",
    "emergency:phone": "144",
    "opening_hours": "24/7",
    "id": "node/6875363551"
  },
  "geometry": {
    "type": "Point",
    "coordinates": [
      8.3992363,
      46.9807249
    ]
  }
}
]
}
